nanobanana_pro_mcp/__init__.py
nanobanana_pro_mcp/server.py
nanobanana_pro_mcp-0.1.1.dist-info/METADATA
nanobanana_pro_mcp-0.1.1.dist-info/WHEEL
nanobanana_pro_mcp-0.1.1.dist-info/entry_points.txt
nanobanana_pro_mcp-0.1.1.dist-info/licenses/LICENSE
nanobanana_pro_mcp-0.1.1.dist-info/RECORD
