Metadata-Version: 2.4
Name: nanobanana-pro-mcp
Version: 0.1.1
Summary: Nano Banana Pro Image Generation for Claude Code - MCP server for automatic image generation, conversion, and smart asset placement
Project-URL: Homepage, https://github.com/rzgrozt/nanobanana-pro-mcp
Project-URL: Repository, https://github.com/rzgrozt/nanobanana-pro-mcp
Project-URL: Issues, https://github.com/rzgrozt/nanobanana-pro-mcp/issues
Author: ruzgar
License-Expression: MIT
License-File: LICENSE
Keywords: ai,assets,claude,image-generation,mcp
Classifier: Development Status :: 4 - Beta
Classifier: Intended Audience :: Developers
Classifier: License :: OSI Approved :: MIT License
Classifier: Programming Language :: Python :: 3
Classifier: Programming Language :: Python :: 3.10
Classifier: Programming Language :: Python :: 3.11
Classifier: Programming Language :: Python :: 3.12
Requires-Python: >=3.10
Requires-Dist: google-generativeai>=0.8.0
Requires-Dist: mcp>=1.0.0
Requires-Dist: pillow>=10.0.0
